[
  {
    "_id": "1fb97438-478a-4006-9535-82233626ba98-0-0-0",
    "text": "e'erninuo",
    "instances": [
      {
        "audSegId": "1fb97438-478a-4006-9535-82233626ba98-0",
        "subSegId": "1fb97438-478a-4006-9535-82233626ba98-0-0",
        "remote": false,
        "cycleGroupId": "1fb97438-478a-4006-9535-82233626ba98-0-0-0",
        "start": 10,
        "end": 19,
        "context": {
          "text": "从一条预警说起，关于e'erninuo ",
          "type": "chinPhrase"
        },
        "target": {
          "text": "e'erninuo",
          "type": "chinFuzz"
        }
      }
    ],
    "target": {
      "text": "e'erninuo",
      "type": "chinFuzz"
    },
    "createdAt": "2026-07-21T05:46:42.849Z",
    "updatedAt": "2026-07-21T08:24:05.931Z"
  },
  {
    "_id": "1fb97438-478a-4006-9535-82233626ba98-0-1-0",
    "text": "厄尔尼诺",
    "instances": [
      {
        "audSegId": "1fb97438-478a-4006-9535-82233626ba98-0",
        "subSegId": "1fb97438-478a-4006-9535-82233626ba98-0-1",
        "remote": false,
        "cycleGroupId": "1fb97438-478a-4006-9535-82233626ba98-0-1-0",
        "start": 0,
        "end": 4,
        "context": {
          "text": "厄尔尼诺",
          "type": "chinWord"
        },
        "target": {
          "text": "厄尔尼诺",
          "type": "chinWord"
        }
      }
    ],
    "target": {
      "text": "厄尔尼诺",
      "type": "chinWord"
    },
    "createdAt": "2026-07-21T05:46:53.046Z",
    "updatedAt": "2026-07-21T08:24:08.761Z"
  },
  {
    "_id": "1fb97438-478a-4006-9535-82233626ba98-1-0-0",
    "text": "一轮厄尔尼诺",
    "instances": [
      {
        "audSegId": "1fb97438-478a-4006-9535-82233626ba98-1",
        "subSegId": "1fb97438-478a-4006-9535-82233626ba98-1-0",
        "remote": false,
        "start": 10,
        "end": 16,
        "context": {
          "text": "今年秋冬季可能会发生一轮厄尔尼诺",
          "type": "chinPhrase"
        },
        "target": {
          "text": "一轮厄尔尼诺",
          "type": "chinPhrase"
        }
      }
    ],
    "target": {
      "text": "一轮厄尔尼诺",
      "type": "chinPhrase"
    },
    "createdAt": "2026-07-21T06:54:35.760Z",
    "updatedAt": "2026-07-21T06:57:03.826Z"
  },
  {
    "_id": "1fb97438-478a-4006-9535-82233626ba98-1-0-1",
    "text": "今年秋冬季",
    "instances": [
      {
        "audSegId": "1fb97438-478a-4006-9535-82233626ba98-1",
        "subSegId": "1fb97438-478a-4006-9535-82233626ba98-1-0",
        "remote": false,
        "start": 0,
        "end": 5,
        "context": {
          "text": "今年秋冬季可能会发生一轮厄尔尼诺",
          "type": "chinPhrase"
        },
        "target": {
          "text": "今年秋冬季",
          "type": "chinPhrase"
        }
      }
    ],
    "target": {
      "text": "今年秋冬季",
      "type": "chinPhrase"
    },
    "createdAt": "2026-07-21T06:54:44.298Z",
    "updatedAt": "2026-07-21T06:57:03.826Z"
  },
  {
    "_id": "1fb97438-478a-4006-9535-82233626ba98-1-0-2",
    "text": "消息",
    "instances": [
      {
        "audSegId": "1fb97438-478a-4006-9535-82233626ba98-1",
        "subSegId": "1fb97438-478a-4006-9535-82233626ba98-1-0",
        "remote": false,
        "start": 19,
        "end": 21,
        "context": {
          "text": "这个消息又被进一步升级了",
          "type": "chinPhrase"
        },
        "target": {
          "text": "消息",
          "type": "chinWord"
        }
      }
    ],
    "target": {
      "text": "消息",
      "type": "chinWord"
    },
    "createdAt": "2026-07-21T06:54:49.359Z",
    "updatedAt": "2026-07-21T06:57:03.826Z"
  },
  {
    "_id": "1fb97438-478a-4006-9535-82233626ba98-0-2-0",
    "text": "厄",
    "instances": [
      {
        "audSegId": "1fb97438-478a-4006-9535-82233626ba98-0",
        "subSegId": "1fb97438-478a-4006-9535-82233626ba98-0-2",
        "remote": false,
        "start": 0,
        "end": 1,
        "context": {
          "text": "厄",
          "type": "chinPhrase"
        },
        "target": {
          "text": "厄",
          "type": "chinChar"
        }
      }
    ],
    "target": {
      "text": "厄",
      "type": "chinChar"
    },
    "createdAt": "2026-07-21T07:34:13.587Z",
    "updatedAt": "2026-07-21T07:34:13.587Z"
  },
  {
    "_id": "1fb97438-478a-4006-9535-82233626ba98-0-0-1",
    "text": "预警",
    "instances": [
      {
        "audSegId": "1fb97438-478a-4006-9535-82233626ba98-0",
        "subSegId": "1fb97438-478a-4006-9535-82233626ba98-0-0",
        "remote": false,
        "start": 3,
        "end": 5,
        "context": {
          "text": "从一条预警说起，关于e'erninuo ",
          "type": "chinPhrase"
        },
        "target": {
          "text": "预警",
          "type": "chinWord"
        }
      }
    ],
    "target": {
      "text": "预警",
      "type": "chinWord"
    },
    "createdAt": "2026-07-21T08:24:05.931Z",
    "updatedAt": "2026-07-21T08:24:05.931Z"
  }
]
